ipysketch/__init__.py
ipysketch/__main__.py
ipysketch/app.py
ipysketch/buttons.py
ipysketch/canvas.py
ipysketch/constants.py
ipysketch/controller.py
ipysketch/ipywidget.py
ipysketch/model.py
ipysketch/assets/colors.png
ipysketch/assets/delete-60.png
ipysketch/assets/eraser-60.png
ipysketch/assets/lasso-80.png
ipysketch/assets/logo.ico
ipysketch/assets/logo.png
ipysketch/assets/move-60.png
ipysketch/assets/move.png
ipysketch/assets/pen-60.png
ipysketch/assets/redo-50.png
ipysketch/assets/rotation-124.png
ipysketch/assets/save-60.png
ipysketch/assets/save-disabled-60.png
ipysketch/assets/scale-124.png
ipysketch/assets/shapes-124.png
ipysketch/assets/undo-50.png
ipysketch-0.2.2.dist-info/LICENSE
ipysketch-0.2.2.dist-info/METADATA
ipysketch-0.2.2.dist-info/WHEEL
ipysketch-0.2.2.dist-info/top_level.txt
ipysketch-0.2.2.dist-info/RECORD
