Metadata-Version: 2.1
Name: ipysketch
Version: 0.2.2
Summary: Handwriting and sketching in Jupyter notebooks
Home-page: https://github.com/maroba/ipysketch
Author: Matthias Baer
Author-email: matthias.r.baer@googlemail.com
License: GPLv3
Platform: ALL
Classifier: Operating System :: OS Independent
Classifier: Programming Language :: Python :: 3
Requires-Python: >=3.6
License-File: LICENSE
Requires-Dist: sphinx
Requires-Dist: ipywidgets
Requires-Dist: ipython
Requires-Dist: scikit-image
Requires-Dist: Pillow
Requires-Dist: setuptools
Requires-Dist: scipy
Requires-Dist: Shapely
Requires-Dist: numpy
